pcw_regrs_py-1.10.2.dist-info/METADATA
pcw_regrs_py-1.10.2.dist-info/WHEEL
pcw_regrs_py/__init__.py
pcw_regrs_py/_example.py
pcw_regrs_py/pcw_regrs_py.cpython-39-i386-linux-gnu.so
pcw_regrs_py-1.10.2.dist-info/RECORD
